pyrtid/__about__.py
pyrtid/__init__.py
pyrtid/forward/__init__.py
pyrtid/forward/flow_solver.py
pyrtid/forward/geochem_solver.py
pyrtid/forward/models.py
pyrtid/forward/solver.py
pyrtid/forward/transport_solver.py
pyrtid/inverse/__init__.py
pyrtid/inverse/executors.py
pyrtid/inverse/gradient.py
pyrtid/inverse/loss_function.py
pyrtid/inverse/model.py
pyrtid/inverse/obs.py
pyrtid/inverse/params.py
pyrtid/inverse/preconditioner.py
pyrtid/inverse/adjoint/__init__.py
pyrtid/inverse/adjoint/aflow_solver.py
pyrtid/inverse/adjoint/ageochem_solver.py
pyrtid/inverse/adjoint/amain_solver.py
pyrtid/inverse/adjoint/amodels.py
pyrtid/inverse/adjoint/atransport_solver.py
pyrtid/inverse/regularization/__init__.py
pyrtid/inverse/regularization/aca.py
pyrtid/inverse/regularization/base.py
pyrtid/inverse/regularization/covariances.py
pyrtid/inverse/regularization/dense.py
pyrtid/inverse/regularization/drift.py
pyrtid/inverse/regularization/geostatistical.py
pyrtid/inverse/regularization/hmatrix.py
pyrtid/inverse/regularization/tikhonov.py
pyrtid/inverse/regularization/toeplitz.py
pyrtid/inverse/regularization/tree.py
pyrtid/inverse/regularization/tv.py
pyrtid/plot/__init__.py
pyrtid/plot/obs_vs_simu.py
pyrtid/utils/__init__.py
pyrtid/utils/dataclass.py
pyrtid/utils/enum.py
pyrtid/utils/finite_differences.py
pyrtid/utils/grid.py
pyrtid/utils/means.py
pyrtid/utils/operators.py
pyrtid/utils/optimize.py
pyrtid/utils/random_field.py
pyrtid/utils/spatial_filters.py
pyrtid/utils/spde.py
pyrtid/utils/types.py
pyrtid/utils/versions.py
pyrtid/utils/wellfield.py
tests/__init__.py
tests/forward/test_models.py
tests/forward/test_solver.py
tests/inverse/test_covariances.py
tests/inverse/test_drift.py
tests/inverse/test_params.py
tests/inverse/test_reg_geostatistics.py
tests/inverse/test_reg_local.py
tests/inverse/test_tree.py
tests/plot/test_obs_vs_simu.py
tests/utils/test_dataclass.py
tests/utils/test_enum.py
tests/utils/test_finite_differences.py
tests/utils/test_grid.py
pyrtid-0.1.1.dist-info/AUTHORS.rst
pyrtid-0.1.1.dist-info/LICENSE
pyrtid-0.1.1.dist-info/METADATA
pyrtid-0.1.1.dist-info/WHEEL
pyrtid-0.1.1.dist-info/top_level.txt
pyrtid-0.1.1.dist-info/RECORD
