Metadata-Version: 2.1
Name: pyrtid
Version: 0.1.1
Summary: Reactive Transport Inversion demonstrator written in Python.
Home-page: https://github.com/pyrtid/pyrtid
Author: attr: pyrtid.__author__
Author-email: antoinecollet5@gmail.com
License: MIT license
Keywords: Inversion,Gradient descent,Reactive transport,Parameters estimation,Adjoint State,Demonstrator
Classifier: Development Status :: 2 - Pre-Alpha
Classifier: Intended Audience :: Developers
Classifier: License :: OSI Approved :: MIT License
Classifier: Natural Language :: English
Classifier: Programming Language :: Python :: 3
Classifier: Programming Language :: Python :: 3.7
Classifier: Programming Language :: Python :: 3.8
Classifier: Programming Language :: Python :: 3.9
Classifier: Programming Language :: Python :: 3.10
Classifier: Programming Language :: Python :: 3.11
Requires-Python: <4,>=3.7
License-File: LICENSE
License-File: AUTHORS.rst
Requires-Dist: importlib-metadata
Requires-Dist: numpy
